Metadata-Version: 1.1
Name: clhs
Version: 1.0.2
Summary: Conditioned Latin Hypercube Sampling in Python
Home-page: https://github.com/wagoner47/clhs_py
Author: Erika Wagoner
Author-email: wagoner47+clhs@email.arizona.edu
License: MIT
Platform: UNKNOWN
Classifier: Programming Language :: Python :: 3
Classifier: Development Status :: 2 - Pre-Alpha
Classifier: Intended Audience :: Science/Research
Classifier: License :: OSI Approved :: MIT License
Classifier: Natural Language :: English
Classifier: Topic :: Scientific/Engineering
Classifier: Topic :: Scientific/Engineering :: Astronomy
